vyper_tree/__init__.py
vyper_tree/__main__.py
vyper_tree/main.py
vyper_tree-0.1.12.dist-info/entry_points.txt
vyper_tree-0.1.12.dist-info/WHEEL
vyper_tree-0.1.12.dist-info/METADATA
vyper_tree-0.1.12.dist-info/RECORD
