Metadata-Version: 2.1
Name: vyper-tree
Version: 0.1.12
Summary: 
Home-page: https://github.com/z80dev/vyper-tree
Author: z80
Author-email: z80@ophy.xyz
Requires-Python: >=3.10,<3.11
Classifier: Programming Language :: Python :: 3
Classifier: Programming Language :: Python :: 3.10
Requires-Dist: rich (>=12.5.1,<13.0.0)
Requires-Dist: vyper (>=0.3.4)
Project-URL: Repository, https://github.com/z80dev/vyper-tree
